{
    "subprocess": "retractable",
    "name": "Retractable",
    "id": 4,
    "parameters": [
        {
            "facility": {
                "name": "Salt Lake City",
                "id": 28,
                "enabled": true
            },
            "processes": [
                "13ozBanner",
                "DSS",
                "UV Fabric"
            ],
            "properties": {
                "mixed": false,
                "undersize": "Default",
                "orientationCheck": true
            },
            "overrides": {
                "matInfo": {
                },
                "product": {
                    "pageHandling": "OnePerPage",
                    "customLabel": {
                        "apply": true
                    }
                },
                "data": {
                    "sideMix": 1
                }
            }
        },
        {
            "facility": {
                "name": "Wixom",
                "id": 37,
                "enabled": true
            },
            "processes": [
                "13oz-Matte",
                "13oz-Smooth",
                "UV-Fabric",
                "13oz-PolyFilm"
            ],
            "properties": {
                "mixed": true,
                "undersize": "Default",
                "orientationCheck": true
            },
            "overrides": {
                "matInfo": {
                },
                "product": {
                    "pageHandling": "OnePerPage",
                    "customLabel": {
                        "apply": true
                    }
                },
                "data": {
                    "sideMix": 1
                }
            }
        },
        {
            "facility": {
                "name": "Arlington",
                "id": 5,
                "enabled": true
            },
            "processes": [
                "13oz-Matte",
                "13oz-Smooth",
                "UV-Fabric",
                "13oz-PolyFilm"
            ],
            "properties": {
                "mixed": true,
                "undersize": "Default",
                "orientationCheck": true
            },
            "overrides": {
                "matInfo": {
                },
                "product": {
                    "pageHandling": "OnePerPage",
                    "customLabel": {
                        "apply": true
                    }
                },
                "data": {
                    "sideMix": 1
                }
            }
        }
    ]
}